{
  "markdown:toggle-preview": [
    {
      "modifiers": [
        "Alt"
      ],
      "key": "A"
    }
  ],
  "app:go-back": [
    {
      "modifiers": [
        "Mod"
      ],
      "key": "E"
    }
  ],
  "app:toggle-left-sidebar": [
    {
      "modifiers": [
        "Mod"
      ],
      "key": "B"
    }
  ],
  "editor:focus-right": [
    {
      "modifiers": [
        "Alt"
      ],
      "key": "D"
    }
  ],
  "editor:focus-left": [
    {
      "modifiers": [
        "Alt"
      ],
      "key": "S"
    }
  ]
}